{
    "title": {
        "title": "Yogya Gamage",
        "link": "/"
    },
    "content": [
        {
            "title" : "Home",
            "link" : "/"
        },
        {
            "title" : "About",
            "link" : "/aboutMe"
        },
        {
            "title" : "Research",
            "link" : "/research"
        },
        {
            "title" : "Experiences",
            "link" : "/experiences"
        },
        {
            "title" : "CV",
            "link" : "https://drive.google.com/drive/folders/1YVH9u20dvRnpbLfl5OossgEpSQOrzYgG?usp=sharing",
            "target" : "_blank"
        }
    ]
}